LICENSE
MANIFEST.in
README.rst
hexgridgeo.py
setup.py
test.py
hexgridgeo_py.egg-info/PKG-INFO
hexgridgeo_py.egg-info/SOURCES.txt
hexgridgeo_py.egg-info/dependency_links.txt
hexgridgeo_py.egg-info/requires.txt
hexgridgeo_py.egg-info/top_level.txt