Metadata-Version: 1.1
Name: hexgridgeo-py
Version: 1.1
Summary: HexGrid Geo
Home-page: https://github.com/gojuno/hexgridgeo-py
Author: Alexander Verbitsky
Author-email: averbitsky@gojuno.com
License: BSD
Keywords: hexgridgeo
Platform: UNKNOWN
Classifier: Development Status :: 5 - Production/Stable
Classifier: Topic :: Utilities
Classifier: Programming Language :: Python :: 3.5
Classifier: License :: OSI Approved :: BSD License
